zeff/__init__.py
zeff/pipeline.py
zeff/pipeline_observation.py
zeff/predictor.py
zeff/uploader.py
zeff/zeffcloud.py
zeff/zeffcloud.yml
zeff/zeffdatasettype.py
zeff/cli/RecordBuilder.template
zeff/cli/RecordGenerator.template
zeff/cli/__init__.py
zeff/cli/__main__.py
zeff/cli/actions.py
zeff/cli/configuration.py
zeff/cli/configuration_default.conf
zeff/cli/init.py
zeff/cli/logging_default.txt
zeff/cli/models.py
zeff/cli/pipeline.py
zeff/cli/predict.py
zeff/cli/record_builders.py
zeff/cli/server.py
zeff/cli/train.py
zeff/cli/upload.py
zeff/cloud/__init__.py
zeff/cloud/dataset.py
zeff/cloud/encoder.py
zeff/cloud/exception.py
zeff/cloud/model.py
zeff/cloud/record.py
zeff/cloud/resource.py
zeff/cloud/training.py
zeff/record/__init__.py
zeff/record/file.py
zeff/record/formatter.py
zeff/record/record.py
zeff/record/structureddata.py
zeff/record/symbolic.py
zeff/record/unstructureddata.py
zeff/record/unstructuredtemporaldata.py
zeff/recordgenerator/__init__.py
zeff/recordgenerator/generate.py
zeff/recordgenerator/urlgenerators.py
zeff/validator/__init__.py
zeff/validator/generic.py
zeff/validator/geospatial.py
zeff/validator/record.py
zeff/validator/temporal.py
ZeffClient-1.0.3.dist-info/LICENSE
ZeffClient-1.0.3.dist-info/METADATA
ZeffClient-1.0.3.dist-info/WHEEL
ZeffClient-1.0.3.dist-info/entry_points.txt
ZeffClient-1.0.3.dist-info/top_level.txt
ZeffClient-1.0.3.dist-info/RECORD
