Metadata-Version: 2.1
Name: ZeffClient
Version: 1.0.3
Summary: ZeffClient is a command line tool & library for working with Zeff AI Cloud API.
Home-page: https://github.com/zeff-ai/ZeffClient
Author: Lance Finn Helsten
Author-email: lanhel@zeff.ai
License: UNKNOWN
Project-URL: Documentation, https://docs.zeff.ai/zeffclient/latest
Project-URL: Source, https://github.com/zeff-ai/ZeffClient
Project-URL: Tracker, https://github.com/zeff-ai/ZeffClient/issues
Project-URL: Contributing, https://github.com/zeff-ai/ZeffClient/blob/master/CONTRIBUTING.rst
Keywords: machine learning
Platform: UNKNOWN
Classifier: Development Status :: 5 - Production/Stable
Classifier: Environment :: Console
Classifier: Intended Audience :: Developers
Classifier: Intended Audience :: Financial and Insurance Industry
Classifier: Intended Audience :: Healthcare Industry
Classifier: Intended Audience :: Healthcare Industry
Classifier: Intended Audience :: Manufacturing
Classifier: Intended Audience :: Science/Research
Classifier: License :: OSI Approved :: Apache Software License
Classifier: Operating System :: POSIX
Classifier: Operating System :: OS Independent
Classifier: Programming Language :: Python :: 3.7
Classifier: Programming Language :: Python :: 3.8
Classifier: Programming Language :: Python :: 3 :: Only
Classifier: Topic :: Scientific/Engineering
Classifier: Topic :: Scientific/Engineering :: Artificial Intelligence
Classifier: Topic :: Scientific/Engineering :: Image Recognition
Classifier: Topic :: Scientific/Engineering :: Information Analysis
Requires-Python: >=3.7
Requires-Dist: PyYAML (>=5.0)
Requires-Dist: requests (>=2.22)
Requires-Dist: tqdm (>=4.0)
Provides-Extra: dev
Requires-Dist: pre-commit (>=1.0) ; extra == 'dev'
Requires-Dist: setup-cfg-fmt (>=1.0) ; extra == 'dev'
Provides-Extra: docs
Requires-Dist: docutils (>=0.3) ; extra == 'docs'
Requires-Dist: Sphinx (>=2.0) ; extra == 'docs'
Requires-Dist: sphinxcontrib-plantuml (>=0.0) ; extra == 'docs'
Requires-Dist: awscli (>=1.0) ; extra == 'docs'
Requires-Dist: towncrier (>=19.0) ; extra == 'docs'
Requires-Dist: gitpython (>=3.0) ; extra == 'docs'
Provides-Extra: examples
Requires-Dist: lxml (>=4.0) ; extra == 'examples'
Provides-Extra: lint
Requires-Dist: black ; extra == 'lint'
Requires-Dist: pylint (>=2.3) ; extra == 'lint'
Requires-Dist: pycodestyle (>=2.5) ; extra == 'lint'
Requires-Dist: pydocstyle (>=3.0) ; extra == 'lint'
Requires-Dist: mypy (>=0.710) ; extra == 'lint'
Provides-Extra: tests
Requires-Dist: pytest (>=4.6) ; extra == 'tests'
Requires-Dist: pytest-cov (>=2.7) ; extra == 'tests'
Requires-Dist: coverage[toml] (>=5.0) ; extra == 'tests'
Requires-Dist: hypothesis (>=4.23) ; extra == 'tests'
